AsyncExclusivePeriods/AsyncExclusivePeriod.py
AsyncExclusivePeriods/__init__.py
AsyncExclusivePeriods-1.12.dist-info/LICENSE
AsyncExclusivePeriods-1.12.dist-info/METADATA
AsyncExclusivePeriods-1.12.dist-info/WHEEL
AsyncExclusivePeriods-1.12.dist-info/top_level.txt
AsyncExclusivePeriods-1.12.dist-info/RECORD
